cal_pro/2_plot.py
cal_pro/3_plot.py
cal_pro/__init__.py
cal_pro/cal.py
cal_pro/definite_integral.py
cal_pro/deriviation.py
cal_pro/double_integral.py
"cal_pro/double_plot(x,y).py"
"cal_pro/double_plot(x,z).py"
"cal_pro/double_plot(y,z).py"
cal_pro/equation.py
cal_pro/exp_eq.py
cal_pro/integral.py
cal_pro/myfunctions.py
cal_pro/plot.py
cal_pro/triple_integral.py
tests/__init__.py
tests/test_myfunctions.py
cal_pro-0.1.4.dist-info/METADATA
cal_pro-0.1.4.dist-info/WHEEL
cal_pro-0.1.4.dist-info/top_level.txt
cal_pro-0.1.4.dist-info/RECORD
