Metadata-Version: 2.1
Name: cal-pro
Version: 0.1.4
Summary: A pro calculator in which helps you to integarate, deriviate, plot, or even do simple calculation; You can also find the answer of equations.
Home-page: https://medium-multiply.readthedocs.io/
Author: MohammadAmin Mohammadion Shabestari, Mohammad Sina Parvizi Motlagh, Mohammad Goleijani
Author-email: shabestari8303@gmail.com , sina.sipamo@gmail.com, golijanimohammad@gmail.com
License: MIT
Platform: UNKNOWN
Classifier: Intended Audience :: Developers
Classifier: License :: OSI Approved :: MIT License
Classifier: Programming Language :: Python
Classifier: Programming Language :: Python :: 3
Classifier: Programming Language :: Python :: 3.6
Classifier: Programming Language :: Python :: 3.7
Classifier: Programming Language :: Python :: 3.8
Classifier: Programming Language :: Python :: 3.9
Classifier: Operating System :: OS Independent
Requires-Dist: matplotlib
Requires-Dist: numpy
Requires-Dist: scipy
Requires-Dist: sympy
